ATE/README.md
ATE/__init__.py
ATE/TCC/README.md
ATE/TES/README.md
ATE/data/README.md
ATE/data/__init__.py
ATE/data/Measurements/README.md
ATE/data/Measurements/__init__.py
ATE/data/Measurements/measurement.py
ATE/data/Metis/README.md
ATE/data/Metis/__init__.py
ATE/data/Metis/metis.py
ATE/data/RegMap/README.md
ATE/data/RegMap/README1.md
ATE/data/RegMap/__init__.py
ATE/data/RegMap/new.regmap
ATE/data/RegMap/new2.regmap
ATE/data/RegMap/register_map_abc.py
ATE/data/RegMap/utils/__init__.py
ATE/data/RegMap/utils/varia.py
ATE/data/RegMap/utils/regedit/MainWindow.py
ATE/data/RegMap/utils/regedit/MainWindow.ui
ATE/data/RegMap/utils/regedit/__init__.py
ATE/data/RegMap/utils/regedit/regedit.py
ATE/data/SEDF/README.md
ATE/data/SEDF/__init__.py
ATE/data/SEDF/records.py
ATE/data/SEDF/utils.py
ATE/data/STDF/README.md
ATE/data/STDF/TODO.md
ATE/data/STDF/__init__.py
ATE/data/STDF/records.py
ATE/data/STDF/utils.py
ATE/doc/README.md
ATE/doc/plugin-system.png
ATE/doc/plugin-system.pptx
ATE/spyder/__init__.py
ATE/spyder/api.py
ATE/spyder/plugin.py
ATE/spyder/project.py
ATE/spyder/widgets/Plugins.md
ATE/spyder/widgets/__init__.py
ATE/spyder/widgets/abc.py
ATE/spyder/widgets/abc_definition.py
ATE/spyder/widgets/api.py
ATE/spyder/widgets/constants.py
ATE/spyder/widgets/main_widget.py
ATE/spyder/widgets/navigation.py
ATE/spyder/widgets/plugin.py
ATE/spyder/widgets/project.py
ATE/spyder/widgets/toolbar.md
ATE/spyder/widgets/toolbar_original.py
ATE/spyder/widgets/validation.py
ATE/spyder/widgets/actions_on/__init__.py
ATE/spyder/widgets/actions_on/dependencies.xlsx
ATE/spyder/widgets/actions_on/device/DeviceItem.py
ATE/spyder/widgets/actions_on/device/EditDeviceWizard.py
ATE/spyder/widgets/actions_on/device/NewDeviceWizard.py
ATE/spyder/widgets/actions_on/device/NewDeviceWizard.ui
ATE/spyder/widgets/actions_on/device/ViewDeviceWizard.py
ATE/spyder/widgets/actions_on/device/__init__.py
ATE/spyder/widgets/actions_on/die/Constants.py
ATE/spyder/widgets/actions_on/die/DieItem.py
Semi_ATE-0.1.0.dev0.dist-info/AUTHORS.rst
Semi_ATE-0.1.0.dev0.dist-info/LICENSE.txt
Semi_ATE-0.1.0.dev0.dist-info/METADATA
Semi_ATE-0.1.0.dev0.dist-info/WHEEL
Semi_ATE-0.1.0.dev0.dist-info/entry_points.txt
Semi_ATE-0.1.0.dev0.dist-info/top_level.txt
Semi_ATE-0.1.0.dev0.dist-info/RECORD
